minio_storage/__init__.py
minio_storage/minio_storage.py
minio_storage-0.1.5.dist-info/METADATA
minio_storage-0.1.5.dist-info/WHEEL
minio_storage-0.1.5.dist-info/top_level.txt
minio_storage-0.1.5.dist-info/RECORD
