Metadata-Version: 2.1
Name: minio-storage
Version: 0.1.5
Summary: minio simplified
Author: holmeschang
Author-email: yangloong@live.com.my
Classifier: Programming Language :: Python :: 3
Classifier: License :: OSI Approved :: MIT License
Classifier: Operating System :: OS Independent
Requires-Python: >=3.6
Requires-Dist: minio >=7.2.7
Requires-Dist: neuon >=0.0.1
